LICENSE
MANIFEST.in
README.md
pyproject.toml
setup.cfg
setup.py
extrafiles/completion.fish
extrafiles/completion.sh
xbstrap/__init__.py
xbstrap/__main__.py
xbstrap/base.py
xbstrap/cli_utils.py
xbstrap/exceptions.py
xbstrap/schema.yml
xbstrap/subpkgs.py
xbstrap/util.py
xbstrap/vcs_utils.py
xbstrap/xbps_utils.py
xbstrap.egg-info/PKG-INFO
xbstrap.egg-info/SOURCES.txt
xbstrap.egg-info/dependency_links.txt
xbstrap.egg-info/entry_points.txt
xbstrap.egg-info/requires.txt
xbstrap.egg-info/top_level.txt
xbstrap/mirror/__init__.py
xbstrap/mirror/__main__.py
xbstrap/pipeline/__init__.py
xbstrap/pipeline/__main__.py