Metadata-Version: 2.1
Name: xbstrap
Version: 0.34.2
Home-page: https://github.com/managarm/xbstrap
Author: Alexander van der Grinten
Author-email: alexander.vandergrinten@gmail.com
License: MIT
Provides-Extra: test
License-File: LICENSE
